[
    {
      "filename": "openspaces.md",
      "attr":
      {
	"data-autoslide": 5000,
	"data-background-image": "resources/images/chef-after-dark.png"
      }
    },
    {
        "filename": "1.html",
        "attr": {
            "data-background-image": "resources/images/openspaces/01-openspaces.png",
            "data-background-size": "contain"
        }
   },
    {
        "filename": "2.html",
        "attr": {
            "data-background-image": "resources/images/openspaces/02-openspaces.png",
            "data-background-size": "contain"
        }
   },
    {
        "filename": "3.html",
        "attr": {
            "data-background-image": "resources/images/openspaces/03-openspaces.png",
            "data-background-size": "contain"
        }
   },
    {
        "filename": "4.html",
        "attr": {
            "data-background-image": "resources/images/openspaces/04-openspaces.png",
            "data-background-size": "contain"
        }
   },
    {
        "filename": "5.html",
        "attr": {
            "data-background-image": "resources/images/openspaces/05-openspaces.png",
            "data-background-size": "contain"
        }
   },
    {
        "filename": "6.html",
        "attr": {
            "data-background-image": "resources/images/openspaces/06-openspaces.png",
            "data-background-size": "contain"
        }
   },
    {
        "filename": "7.html",
        "attr": {
            "data-background-image": "resources/images/openspaces/07-openspaces.png",
            "data-background-size": "contain"
        }
   },
    {
        "filename": "8.html",
        "attr": {
            "data-background-image": "resources/images/openspaces/08-openspaces.png",
            "data-background-size": "contain"
        }
   },
    {
        "filename": "9.html",
        "attr": {
            "data-background-image": "resources/images/openspaces/09-openspaces.png",
            "data-background-size": "contain"
        }
   },
    {
        "filename": "10.html",
        "attr": {
            "data-background-image": "resources/images/openspaces/10-openspaces.png",
            "data-background-size": "contain"
        }
   },
    {
        "filename": "11.html",
        "attr": {
            "data-background-image": "resources/images/openspaces/11-openspaces.png",
            "data-background-size": "contain"
        }
   },
    {
        "filename": "12.html",
        "attr": {
            "data-background-image": "resources/images/openspaces/12-openspaces.png",
            "data-background-size": "contain"
        }
   },
    {
        "filename": "13.html",
        "attr": {
            "data-background-image": "resources/images/openspaces/13-openspaces.png",
            "data-background-size": "contain"
        }
   },
    {
        "filename": "14.html",
        "attr": {
            "data-background-image": "resources/images/openspaces/14-openspaces.png",
            "data-background-size": "contain"
        }
   },
    {
        "filename": "15.html",
        "attr": {
            "data-background-image": "resources/images/openspaces/15-openspaces.png",
            "data-background-size": "contain"
        }
   },
    {
        "filename": "16.html",
        "attr": {
            "data-background-image": "resources/images/openspaces/16-openspaces.png",
            "data-background-size": "contain"
        }
   },
    {
        "filename": "17.html",
        "attr": {
            "data-background-image": "resources/images/openspaces/17-openspaces.png",
            "data-background-size": "contain"
        }
   },
    {
        "filename": "18.html",
        "attr": {
            "data-background-image": "resources/images/openspaces/18-openspaces.png",
            "data-background-size": "contain"
        }
   },
    {
        "filename": "19.html",
        "attr": {
            "data-background-image": "resources/images/openspaces/19-openspaces.png",
            "data-background-size": "contain"
        }
   },
    {
        "filename": "20.html",
        "attr": {
            "data-background-image": "resources/images/openspaces/20-openspaces.png",
            "data-background-size": "contain"
        }
   }]
